openstef_beam/__init__.py
openstef_beam/analysis/__init__.py
openstef_beam/analysis/analysis_pipeline.py
openstef_beam/analysis/models/__init__.py
openstef_beam/analysis/models/target_metadata.py
openstef_beam/analysis/models/visualization_aggregation.py
openstef_beam/analysis/models/visualization_output.py
openstef_beam/analysis/plots/__init__.py
openstef_beam/analysis/plots/forecast_time_series_plotter.py
openstef_beam/analysis/plots/grouped_target_metric_plotter.py
openstef_beam/analysis/plots/precision_recall_curve_plotter.py
openstef_beam/analysis/plots/quantile_calibration_box_plotter.py
openstef_beam/analysis/plots/quantile_probability_plotter.py
openstef_beam/analysis/plots/summary_table_plotter.py
openstef_beam/analysis/plots/windowed_metric_plotter.py
openstef_beam/analysis/visualizations/__init__.py
openstef_beam/analysis/visualizations/base.py
openstef_beam/analysis/visualizations/grouped_target_metric_visualization.py
openstef_beam/analysis/visualizations/precision_recall_curve_visualization.py
openstef_beam/analysis/visualizations/quantile_calibration_box_visualization.py
openstef_beam/analysis/visualizations/quantile_probability_visualization.py
openstef_beam/analysis/visualizations/summary_table_visualization.py
openstef_beam/analysis/visualizations/timeseries_visualization.py
openstef_beam/analysis/visualizations/windowed_metric_visualization.py
openstef_beam/backtesting/__init__.py
openstef_beam/backtesting/backtest_callback.py
openstef_beam/backtesting/backtest_event.py
openstef_beam/backtesting/backtest_event_generator.py
openstef_beam/backtesting/backtest_pipeline.py
openstef_beam/backtesting/restricted_horizon_timeseries.py
openstef_beam/backtesting/backtest_forecaster/__init__.py
openstef_beam/backtesting/backtest_forecaster/dummy_forecaster.py
openstef_beam/backtesting/backtest_forecaster/mixins.py
openstef_beam/benchmarking/__init__.py
openstef_beam/benchmarking/benchmark_comparison_pipeline.py
openstef_beam-4.0.0a10.dist-info/METADATA
openstef_beam-4.0.0a10.dist-info/WHEEL
openstef_beam-4.0.0a10.dist-info/RECORD
