Metadata-Version: 2.4
Name: openstef-beam
Version: 4.0.0a10
Summary: Backtesting, Evaluation, Analysis and Metrics (BEAM) library for OpenSTEF
Project-URL: Documentation, https://openstef.github.io/openstef/index.html
Project-URL: Homepage, https://lfenergy.org/projects/openstef/
Project-URL: Issues, https://github.com/OpenSTEF/openstef/issues
Project-URL: Repository, https://github.com/OpenSTEF/openstef
Author-email: "Alliander N.V" <openstef@lfenergy.org>
License-Expression: MPL-2.0
Keywords: energy,forecasting,machinelearning
Classifier: Development Status :: 5 - Production/Stable
Classifier: Intended Audience :: Developers
Classifier: Programming Language :: Python :: 3 :: Only
Classifier: Programming Language :: Python :: 3.12
Classifier: Programming Language :: Python :: 3.13
Classifier: Programming Language :: Python :: 3.14
Requires-Python: <4.0,>=3.12
Requires-Dist: openstef-core<5,>=4.0.0.dev0
Requires-Dist: plotly>=6.3
Requires-Dist: pyyaml>=6.0.2
Requires-Dist: scoringrules>=0.8
Requires-Dist: tqdm>=4.67.1
Provides-Extra: all
Requires-Dist: s3fs>=2025.5.1; extra == 'all'
